esa_pds4_packager/__init__.py
esa_pds4_packager/config.py
esa_pds4_packager/java.py
esa_pds4_packager/packager.py
esa_pds4_packager/py.typed
esa_pds4_packager-0.0.1.dist-info/METADATA
esa_pds4_packager-0.0.1.dist-info/WHEEL
esa_pds4_packager-0.0.1.dist-info/licenses/LICENSE
esa_pds4_packager-0.0.1.dist-info/RECORD
