Metadata-Version: 2.4
Name: esa-pds4-packager
Version: 0.0.1
Project-URL: documentation, https://luca-penasa.github.io/esa-pds4-packager
Project-URL: homepage, https://luca-penasa.github.io/esa-pds4-packager
Project-URL: repository, https://github.com/luca-penasa/esa-pds4-packager
Author-email: Luca Penasa <luca.penasa@gmail.com>
License-Expression: MIT
License-File: LICENSE
Classifier: Development Status :: 4 - Beta
Classifier: Intended Audience :: Developers
Classifier: Operating System :: OS Independent
Classifier: Programming Language :: Python
Classifier: Programming Language :: Python :: 3
Classifier: Programming Language :: Python :: 3.10
Classifier: Programming Language :: Python :: 3.11
Classifier: Programming Language :: Python :: 3.12
Classifier: Programming Language :: Python :: 3.13
Classifier: Topic :: Software Development :: Libraries :: Python Modules
Classifier: Typing :: Typed
Requires-Python: <4.0,>=3.10
Requires-Dist: attrs>=25.3.0
Requires-Dist: importlib-metadata<9,>=8.5.0
Requires-Dist: loguru<0.8,>=0.7.2
Requires-Dist: platformdirs>=4.3.8
Requires-Dist: typed-settings[attrs]>=24.6.0
